basapy/__init__.py
basapy/format.py
basapy-0.0.2.dist-info/LICENCE
basapy-0.0.2.dist-info/METADATA
basapy-0.0.2.dist-info/WHEEL
basapy-0.0.2.dist-info/top_level.txt
basapy-0.0.2.dist-info/RECORD
